zana/django/__init__.py
zana/django/apps.py
zana/django/models/__init__.py
zana/django/models/__init__.pyi
zana/django/models/_xaliases.py
zana/django/models/fields/__init__.py
zana/django/models/fields/aliases.py
zana/django/utils/__init__.py
zana/django/utils/operator.py
django_zana-0.2.8.dist-info/WHEEL
django_zana-0.2.8.dist-info/METADATA
django_zana-0.2.8.dist-info/RECORD
